[
  {
    "id": "pizza-hut-bogo",
    "shopName": "Pizza Hut",
    "logo": "./images/pizza hut.png",
    "title": "Pizza Hut Promotions: Buy One Get One Free Pizza",
    "description": "Valid on Large Pan Pizzas. Excludes Supreme & Seafood.",
    "validity": "Until July 31st, 2025",
    "terms": "Terms apply. Dine-in and Takeaway only. Colombo outlets.",
    "url": "https://www.pizzahut.lk/",
    "category": "food"
  },
  {
    "id": "kfc-combo",
    "shopName": "KFC",
    "logo": "./images/KFC.png",
    "title": "KFC Promotions: Zinger Combo Meal Discount",
    "description": "Get Rs. 150 off on Zinger Combo Meal. Valid on app orders.",
    "validity": "Weekdays, 11 AM - 3 PM",
    "terms": "Available at selected outlets. Limited time offer.",
    "url": "https://www.kfc.lk/",
    "category": "food"
  },
  {
    "id": "taco-bell-tuesday",
    "shopName": "Taco Bell",
    "logo": "./images/taco bell.png",
    "title": "Taco Bell Promotions: Taco Tuesday Special",
    "description": "Buy any 2 Tacos, get 1 free! Mix & Match.",
    "validity": "Every Tuesday in July 2025",
    "terms": "Dine-in only. All Colombo branches.",
    "url": "https://www.tacobell.com/",
    "category": "food"
  },
  {
    "id": "subway-feast",
    "shopName": "Subway",
    "logo": "./images/subway.png",
    "title": "Subway Promotions: Footlong Feast Deal",
    "description": "Get a Footlong sub, drink, and cookie for Rs. 1200.",
    "validity": "Ongoing offer",
    "terms": "Participating outlets only. Check in-store for details.",
    "url": "https://www.subway.com/en-AU/Promotions",
    "category": "food"
  },
  {
    "id": "vitos-family",
    "shopName": "Vito's Pizza",
    "logo": "./images/vitos pizza.png",
    "title": "Vito's Pizza Promotions: Weekend Family Combo",
    "description": "2 Large Pizzas, Garlic Bread, and 1.5L drink for Rs. 4500.",
    "validity": "Saturdays & Sundays in July 2025",
    "terms": "Delivery only. Call to order.",
    "url": "https://www.ubereats.com/lk/store/vito-wood-fired-pizza-colombo-07/znaKJhuuXVuX62EnGteyIQ",
    "category": "food"
  },
  {
    "id": "burger-king-whopper",
    "shopName": "Burger King",
    "logo": "./images/bk.png",
    "title": "Burger King Promotions: Whopper Wednesday",
    "description": "Buy one Whopper, get second 50% off.",
    "validity": "Every Wednesday",
    "terms": "Dine-in/Takeaway. Check participating outlets.",
    "url": "https://slashdeals.lk/vendor/burger-king",
    "category": "food"
  },
  {
    "id": "popeyes-feast",
    "shopName": "Popeyes",
    "logo": "./images/Popeyes.png",
    "title": "Popeyes Promotions: Louisiana Fried Chicken Feast",
    "description": "8pc Chicken, 2 Large Sides, 4 Biscuits for Rs. 3800.",
    "validity": "Limited time offer",
    "terms": "Subject to availability.",
    "url": "https://www.ubereats.com/lk/store/popeyes-mount-lavinia/tgSYqD5HStKkVsrW9i4KSg",
    "category": "food"
  },
  {
    "id": "dominos-edv",
    "shopName": "Domino's Pizza",
    "logo": "./images/dominos.png",
    "title": "Domino's Pizza Promotions: Every Day Value (EDV) Deals",
    "description": "Various combo deals available daily. Check website for specifics.",
    "validity": "Ongoing",
    "terms": "Prices and offers may vary by outlet.",
    "url": "https://www.dominos.lk/edv",
    "category": "food"
  },
  {
    "id": "land-of-kings-buffet",
    "shopName": "Land of Kings",
    "logo": "./images/lano of kings.png",
    "title": "Land of Kings Promotions: Special Lunch Buffet",
    "description": "All-you-can-eat Sri Lankan buffet for Rs. 1800.",
    "validity": "Weekdays, 12 PM - 3 PM",
    "terms": "Reservations recommended.",
    "url": "https://landofkingscafe.com/product-category/special-offers/",
    "category": "food"
  },
  {
    "id": "chinese-dragon-family",
    "shopName": "Chinese Dragon Cafe",
    "logo": "./images/chinese dragon.png",
    "title": "Chinese Dragon Cafe Promotions: Family Dinner Pack",
    "description": "Special family meal for 4-5 people with 4 main dishes, rice/noodles.",
    "validity": "Ongoing",
    "terms": "Delivery and Takeaway only.",
    "url": "https://www.chinesedragoncafe.com/pages/promotions",
    "category": "food"
  },
  {
    "id": "odel-seasonal",
    "shopName": "Odel",
    "logo": "./images/aodel.png",
    "title": "Odel Promotions: Seasonal Sale",
    "description": "Up to 30% off on selected fashion and accessories.",
    "validity": "August 1st - 15th, 2025",
    "terms": "In-store and online. Terms and conditions apply.",
    "url": "https://www.odel.lk/",
    "category": "fashion"
  },
  {
    "id": "nolimit-new-collection",
    "shopName": "NoLimit",
    "logo": "./images/anolimit.png",
    "title": "NoLimit Promotions: New Collection Discount",
    "description": "15% off on all new arrivals for loyalty members.",
    "validity": "Entire month of August 2025",
    "terms": "Show loyalty card at checkout.",
    "url": "https://nolimit.lk/",
    "category": "fashion"
  },
  {
    "id": "mimosa-back-to-school",
    "shopName": "Mimosa",
    "logo": "./images/amimosa.png",
    "title": "Mimosa Promotions: Back to School Offers",
    "description": "Special discounts on kids' wear and school uniforms.",
    "validity": "Until August 31st, 2025",
    "terms": "Selected items only.",
    "url": "https://mimosaclothingindia.com/",
    "category": "fashion"
  },
  {
    "id": "kelly-felder-online",
    "shopName": "Kelly Felder",
    "logo": "./images/akelly felder.png",
    "title": "Kelly Felder Promotions: Exclusive Online Discount",
    "description": "20% off your first online order. Use code: KF2025.",
    "validity": "Ongoing online offer",
    "terms": "New customers only. Excludes sale items.",
    "url": "https://kellyfelder.com/",
    "category": "fashion"
  },
  {
    "id": "fashion-bug-clearance",
    "shopName": "Fashion Bug",
    "logo": "./images/afashion bug.png",
    "title": "Fashion Bug Promotions: Mega Clearance Sale",
    "description": "Up to 50% off on men's, women's, and kids' clothing.",
    "validity": "While stocks last",
    "terms": "All outlets participating.",
    "url": "https://fashionbug.lk/",
    "category": "fashion"
  },
  {
    "id": "cool-planet-mid-season",
    "shopName": "Cool Planet",
    "logo": "./images/acool planet.png",
    "title": "Cool Planet Promotions: Mid-Season Extravaganza",
    "description": "Great deals on casual wear and accessories.",
    "validity": "Until end of July 2025",
    "terms": "Selected items.",
    "url": "https://www.coolplanet.lk/",
    "category": "fashion"
  },
  {
    "id": "thilakawardhana-wedding",
    "shopName": "Thilakawardhana Textiles",
    "logo": "./images/athilaka.png",
    "title": "Thilakawardhana Textiles Promotions: Wedding & Occasion Wear Discounts",
    "description": "Special prices on sarees, national wear, and formal attire.",
    "validity": "Limited period",
    "terms": "Visit showroom for details.",
    "url": "https://thilakawardhana.com/",
    "category": "fashion"
  },
  {
    "id": "elite-indian-special",
    "shopName": "Elite Indian",
    "logo": "./images/elite_indian_logo.png",
    "title": "Elite Indian: Daily Lunch Specials",
    "description": "Enjoy authentic Indian cuisine with our rotating daily lunch specials.",
    "validity": "Ongoing",
    "terms": "Dine-in only. Menu changes daily.",
    "url": "https://www.tripadvisor.com/Restaurant_Review-g293962-d12115565-Reviews-Elite_Indian_Restaurant-Colombo_Western_Province.html",
    "category": "food"
  },
  {
    "id": "almas-restaurant-family",
    "shopName": "Almas Restaurant",
    "logo": "./images/almas_restaurant_logo.png",
    "title": "Almas Restaurant: Weekend Family Platters",
    "description": "Generous family platters perfect for sharing. Serves 4-6.",
    "validity": "Weekends only",
    "terms": "Pre-booking recommended. Limited availability.",
    "url": "https://almaas.lk/",
    "category": "food"
  },
  {
    "id": "big-plate-express-lunch",
    "shopName": "Big Plate",
    "logo": "./images/big_plate_logo.png",
    "title": "Big Plate: Express Lunch Combos",
    "description": "Quick and delicious lunch combos for your busy day.",
    "validity": "Weekdays 12 PM - 3 PM",
    "terms": "Dine-in/Takeaway. Check daily specials.",
    "url": "https://www.facebook.com/Bigplatelk/",
    "category": "food"
  },
  {
    "id": "street-burger-value",
    "shopName": "Street Burger",
    "logo": "./images/street_burger_logo.png",
    "title": "Street Burger: Value Burger Deals",
    "description": "Great prices on selected burgers and sides.",
    "validity": "All day, every day",
    "terms": "Limited time offer. Participating outlets.",
    "url": "https://streetburger.lk/",
    "category": "food"
  },
  {
    "id": "la-luna-cafe-offer",
    "shopName": "La Luna",
    "logo": "./images/la_luna_logo.png",
    "title": "La Luna: Evening Cafe Delights",
    "description": "Special offers on our coffee and dessert pairings after 6 PM.",
    "validity": "Daily, 6 PM onwards",
    "terms": "Dine-in only.",
    "url": "https://www.instagram.com/la_luna.cmb/",
    "category": "food"
  },
  {
    "id": "mc-donalds-happy-meal",
    "shopName": "McDonald's",
    "logo": "./images/mcdonalds_logo.png",
    "title": "McDonald's: Happy Meal Surprises",
    "description": "Enjoy special discounts on Happy Meals with new toys.",
    "validity": "Ongoing",
    "terms": "Check in-store for latest toy collection.",
    "url": "https://www.mcdonalds.com/us/en-us.html",
    "category": "food"
  },
  {
    "id": "burleys-bbq-night",
    "shopName": "Burleys",
    "logo": "./images/burleys_logo.png",
    "title": "Burleys: BBQ Night Specials",
    "description": "Indulge in delicious BBQ platters every weekend.",
    "validity": "Friday & Saturday nights",
    "terms": "Reservations recommended.",
    "url": "https://www.facebook.com/burleysfoods/",
    "category": "food"
  },
  {
    "id": "up-down-kandy-style",
    "shopName": "Up Down Kandy",
    "logo": "./images/up_down_kandy_logo.png",
    "title": "Up Down Kandy: New Arrivals Discount",
    "description": "Be the first to get 10% off on our latest fashion collection.",
    "validity": "Limited time",
    "terms": "Selected items only. In-store only.",
    "url": "https://uptownsrilanka.com/",
    "category": "fashion"
  },
  {
    "id": "zigzag-online-exclusive",
    "shopName": "Zig Zag",
    "logo": "./images/zigzag_logo.png",
    "title": "Zig Zag: Online Exclusive Offers",
    "description": "Special discounts only available for online purchases.",
    "validity": "Ongoing online",
    "terms": "Applies to non-sale items.",
    "url": "https://zigzag.lk/",
    "category": "fashion"
  },
  {
    "id": "adidas-sportswear-sale",
    "shopName": "Adidas",
    "logo": "./images/adidas_logo.png",
    "title": "Adidas: Sportswear Clearance",
    "description": "Huge savings on performance wear, shoes, and accessories.",
    "validity": "While stocks last",
    "terms": "Selected models and sizes.",
    "url": "https://odel.lk/adidas/br/189",
    "category": "fashion"
  }
]